woodplotlib/__init__.py
woodplotlib-0.0.1.dist-info/DESCRIPTION.rst
woodplotlib-0.0.1.dist-info/METADATA
woodplotlib-0.0.1.dist-info/RECORD
woodplotlib-0.0.1.dist-info/WHEEL
woodplotlib-0.0.1.dist-info/metadata.json
woodplotlib-0.0.1.dist-info/top_level.txt
